{
   "-" : {
      "body_limit" : {
         "fail" : 0,
         "pass" : 1,
         "undef" : 300
      },
      "body_used" : {
         "fail" : 300,
         "pass" : 1,
         "undef" : 0
      },
      "capitalize_subject" : {
         "fail" : 6,
         "pass" : 295,
         "undef" : 0
      },
      "empty_second_line" : {
         "fail" : 0,
         "pass" : 1,
         "undef" : 300
      },
      "imperative_subject" : {
         "fail" : 244,
         "pass" : 57,
         "undef" : 0
      },
      "no_bulk_change" : {
         "fail" : 13,
         "pass" : 288,
         "undef" : 0
      },
      "no_duplicate" : {
         "fail" : 7,
         "pass" : 294,
         "undef" : 0
      },
      "no_long_message" : {
         "fail" : 27,
         "pass" : 274,
         "undef" : 0
      },
      "no_misspelling" : {
         "fail" : 17,
         "pass" : 284,
         "undef" : 0
      },
      "no_period_subject" : {
         "fail" : 286,
         "pass" : 15,
         "undef" : 0
      },
      "no_short_message" : {
         "fail" : 36,
         "pass" : 265,
         "undef" : 0
      },
      "no_vulgarity" : {
         "fail" : 1,
         "pass" : 300,
         "undef" : 0
      },
      "subject_limit" : {
         "fail" : 57,
         "pass" : 244,
         "undef" : 0
      }
   },
   "aleksey.lashin@gmail.com" : {
      "body_limit" : {
         "fail" : 0,
         "pass" : 1,
         "undef" : 0
      },
      "body_used" : {
         "fail" : 0,
         "pass" : 1,
         "undef" : 0
      },
      "capitalize_subject" : {
         "fail" : 1,
         "pass" : 0,
         "undef" : 0
      },
      "empty_second_line" : {
         "fail" : 0,
         "pass" : 1,
         "undef" : 0
      },
      "imperative_subject" : {
         "fail" : 1,
         "pass" : 0,
         "undef" : 0
      },
      "no_bulk_change" : {
         "fail" : 0,
         "pass" : 1,
         "undef" : 0
      },
      "no_duplicate" : {
         "fail" : 0,
         "pass" : 1,
         "undef" : 0
      },
      "no_long_message" : {
         "fail" : 0,
         "pass" : 1,
         "undef" : 0
      },
      "no_misspelling" : {
         "fail" : 1,
         "pass" : 0,
         "undef" : 0
      },
      "no_period_subject" : {
         "fail" : 0,
         "pass" : 1,
         "undef" : 0
      },
      "no_short_message" : {
         "fail" : 1,
         "pass" : 0,
         "undef" : 0
      },
      "no_vulgarity" : {
         "fail" : 0,
         "pass" : 1,
         "undef" : 0
      },
      "subject_limit" : {
         "fail" : 0,
         "pass" : 1,
         "undef" : 0
      }
   },
   "carsten.hartenfels@googlemail.com" : {
      "body_limit" : {
         "fail" : 0,
         "pass" : 1,
         "undef" : 3
      },
      "body_used" : {
         "fail" : 3,
         "pass" : 1,
         "undef" : 0
      },
      "capitalize_subject" : {
         "fail" : 0,
         "pass" : 4,
         "undef" : 0
      },
      "empty_second_line" : {
         "fail" : 0,
         "pass" : 1,
         "undef" : 3
      },
      "imperative_subject" : {
         "fail" : 3,
         "pass" : 1,
         "undef" : 0
      },
      "no_bulk_change" : {
         "fail" : 0,
         "pass" : 4,
         "undef" : 0
      },
      "no_duplicate" : {
         "fail" : 2,
         "pass" : 2,
         "undef" : 0
      },
      "no_long_message" : {
         "fail" : 0,
         "pass" : 4,
         "undef" : 0
      },
      "no_misspelling" : {
         "fail" : 0,
         "pass" : 4,
         "undef" : 0
      },
      "no_period_subject" : {
         "fail" : 3,
         "pass" : 1,
         "undef" : 0
      },
      "no_short_message" : {
         "fail" : 1,
         "pass" : 3,
         "undef" : 0
      },
      "no_vulgarity" : {
         "fail" : 0,
         "pass" : 4,
         "undef" : 0
      },
      "subject_limit" : {
         "fail" : 0,
         "pass" : 4,
         "undef" : 0
      }
   },
   "dev@michael-monschau.de" : {
      "body_limit" : {
         "fail" : 0,
         "pass" : 0,
         "undef" : 2
      },
      "body_used" : {
         "fail" : 2,
         "pass" : 0,
         "undef" : 0
      },
      "capitalize_subject" : {
         "fail" : 1,
         "pass" : 1,
         "undef" : 0
      },
      "empty_second_line" : {
         "fail" : 0,
         "pass" : 0,
         "undef" : 2
      },
      "imperative_subject" : {
         "fail" : 1,
         "pass" : 1,
         "undef" : 0
      },
      "no_bulk_change" : {
         "fail" : 0,
         "pass" : 2,
         "undef" : 0
      },
      "no_duplicate" : {
         "fail" : 0,
         "pass" : 2,
         "undef" : 0
      },
      "no_long_message" : {
         "fail" : 0,
         "pass" : 2,
         "undef" : 0
      },
      "no_misspelling" : {
         "fail" : 0,
         "pass" : 2,
         "undef" : 0
      },
      "no_period_subject" : {
         "fail" : 0,
         "pass" : 2,
         "undef" : 0
      },
      "no_short_message" : {
         "fail" : 0,
         "pass" : 2,
         "undef" : 0
      },
      "no_vulgarity" : {
         "fail" : 0,
         "pass" : 2,
         "undef" : 0
      },
      "subject_limit" : {
         "fail" : 0,
         "pass" : 2,
         "undef" : 0
      }
   },
   "dotnetby@gmail.com" : {
      "body_limit" : {
         "fail" : 0,
         "pass" : 2,
         "undef" : 420
      },
      "body_used" : {
         "fail" : 420,
         "pass" : 2,
         "undef" : 0
      },
      "capitalize_subject" : {
         "fail" : 99,
         "pass" : 323,
         "undef" : 0
      },
      "empty_second_line" : {
         "fail" : 1,
         "pass" : 1,
         "undef" : 420
      },
      "imperative_subject" : {
         "fail" : 370,
         "pass" : 52,
         "undef" : 0
      },
      "no_bulk_change" : {
         "fail" : 17,
         "pass" : 405,
         "undef" : 0
      },
      "no_duplicate" : {
         "fail" : 227,
         "pass" : 195,
         "undef" : 0
      },
      "no_long_message" : {
         "fail" : 4,
         "pass" : 418,
         "undef" : 0
      },
      "no_misspelling" : {
         "fail" : 1,
         "pass" : 421,
         "undef" : 0
      },
      "no_period_subject" : {
         "fail" : 0,
         "pass" : 422,
         "undef" : 0
      },
      "no_short_message" : {
         "fail" : 176,
         "pass" : 246,
         "undef" : 0
      },
      "no_vulgarity" : {
         "fail" : 0,
         "pass" : 422,
         "undef" : 0
      },
      "subject_limit" : {
         "fail" : 22,
         "pass" : 400,
         "undef" : 0
      }
   },
   "freddy92.online@googlemail.com" : {
      "body_limit" : {
         "fail" : 1,
         "pass" : 5,
         "undef" : 19
      },
      "body_used" : {
         "fail" : 19,
         "pass" : 6,
         "undef" : 0
      },
      "capitalize_subject" : {
         "fail" : 5,
         "pass" : 20,
         "undef" : 0
      },
      "empty_second_line" : {
         "fail" : 0,
         "pass" : 6,
         "undef" : 19
      },
      "imperative_subject" : {
         "fail" : 12,
         "pass" : 13,
         "undef" : 0
      },
      "no_bulk_change" : {
         "fail" : 0,
         "pass" : 25,
         "undef" : 0
      },
      "no_duplicate" : {
         "fail" : 3,
         "pass" : 22,
         "undef" : 0
      },
      "no_long_message" : {
         "fail" : 0,
         "pass" : 25,
         "undef" : 0
      },
      "no_misspelling" : {
         "fail" : 2,
         "pass" : 23,
         "undef" : 0
      },
      "no_period_subject" : {
         "fail" : 0,
         "pass" : 25,
         "undef" : 0
      },
      "no_short_message" : {
         "fail" : 9,
         "pass" : 16,
         "undef" : 0
      },
      "no_vulgarity" : {
         "fail" : 0,
         "pass" : 25,
         "undef" : 0
      },
      "subject_limit" : {
         "fail" : 0,
         "pass" : 25,
         "undef" : 0
      }
   },
   "freddy@frederiks-mbp.speedport_w_724v_09011602_00_015" : {
      "body_limit" : {
         "fail" : 0,
         "pass" : 1,
         "undef" : 34
      },
      "body_used" : {
         "fail" : 34,
         "pass" : 1,
         "undef" : 0
      },
      "capitalize_subject" : {
         "fail" : 27,
         "pass" : 8,
         "undef" : 0
      },
      "empty_second_line" : {
         "fail" : 0,
         "pass" : 1,
         "undef" : 34
      },
      "imperative_subject" : {
         "fail" : 21,
         "pass" : 14,
         "undef" : 0
      },
      "no_bulk_change" : {
         "fail" : 3,
         "pass" : 32,
         "undef" : 0
      },
      "no_duplicate" : {
         "fail" : 4,
         "pass" : 31,
         "undef" : 0
      },
      "no_long_message" : {
         "fail" : 0,
         "pass" : 35,
         "undef" : 0
      },
      "no_misspelling" : {
         "fail" : 5,
         "pass" : 30,
         "undef" : 0
      },
      "no_period_subject" : {
         "fail" : 0,
         "pass" : 35,
         "undef" : 0
      },
      "no_short_message" : {
         "fail" : 9,
         "pass" : 26,
         "undef" : 0
      },
      "no_vulgarity" : {
         "fail" : 0,
         "pass" : 35,
         "undef" : 0
      },
      "subject_limit" : {
         "fail" : 5,
         "pass" : 30,
         "undef" : 0
      }
   },
   "freddy@frederiks-mbp.speedport_w_724v_09011603_00_009" : {
      "body_limit" : {
         "fail" : 0,
         "pass" : 0,
         "undef" : 7
      },
      "body_used" : {
         "fail" : 7,
         "pass" : 0,
         "undef" : 0
      },
      "capitalize_subject" : {
         "fail" : 2,
         "pass" : 5,
         "undef" : 0
      },
      "empty_second_line" : {
         "fail" : 0,
         "pass" : 0,
         "undef" : 7
      },
      "imperative_subject" : {
         "fail" : 2,
         "pass" : 5,
         "undef" : 0
      },
      "no_bulk_change" : {
         "fail" : 4,
         "pass" : 3,
         "undef" : 0
      },
      "no_duplicate" : {
         "fail" : 1,
         "pass" : 6,
         "undef" : 0
      },
      "no_long_message" : {
         "fail" : 0,
         "pass" : 7,
         "undef" : 0
      },
      "no_misspelling" : {
         "fail" : 1,
         "pass" : 6,
         "undef" : 0
      },
      "no_period_subject" : {
         "fail" : 0,
         "pass" : 7,
         "undef" : 0
      },
      "no_short_message" : {
         "fail" : 0,
         "pass" : 7,
         "undef" : 0
      },
      "no_vulgarity" : {
         "fail" : 0,
         "pass" : 7,
         "undef" : 0
      },
      "subject_limit" : {
         "fail" : 2,
         "pass" : 5,
         "undef" : 0
      }
   },
   "git@mariusrackwitz.de" : {
      "body_limit" : {
         "fail" : 0,
         "pass" : 0,
         "undef" : 3
      },
      "body_used" : {
         "fail" : 3,
         "pass" : 0,
         "undef" : 0
      },
      "capitalize_subject" : {
         "fail" : 3,
         "pass" : 0,
         "undef" : 0
      },
      "empty_second_line" : {
         "fail" : 0,
         "pass" : 0,
         "undef" : 3
      },
      "imperative_subject" : {
         "fail" : 2,
         "pass" : 1,
         "undef" : 0
      },
      "no_bulk_change" : {
         "fail" : 1,
         "pass" : 2,
         "undef" : 0
      },
      "no_duplicate" : {
         "fail" : 0,
         "pass" : 3,
         "undef" : 0
      },
      "no_long_message" : {
         "fail" : 0,
         "pass" : 3,
         "undef" : 0
      },
      "no_misspelling" : {
         "fail" : 0,
         "pass" : 3,
         "undef" : 0
      },
      "no_period_subject" : {
         "fail" : 0,
         "pass" : 3,
         "undef" : 0
      },
      "no_short_message" : {
         "fail" : 0,
         "pass" : 3,
         "undef" : 0
      },
      "no_vulgarity" : {
         "fail" : 0,
         "pass" : 3,
         "undef" : 0
      },
      "subject_limit" : {
         "fail" : 0,
         "pass" : 3,
         "undef" : 0
      }
   },
   "github@michael-monschau.de" : {
      "body_limit" : {
         "fail" : 0,
         "pass" : 0,
         "undef" : 1
      },
      "body_used" : {
         "fail" : 1,
         "pass" : 0,
         "undef" : 0
      },
      "capitalize_subject" : {
         "fail" : 0,
         "pass" : 1,
         "undef" : 0
      },
      "empty_second_line" : {
         "fail" : 0,
         "pass" : 0,
         "undef" : 1
      },
      "imperative_subject" : {
         "fail" : 1,
         "pass" : 0,
         "undef" : 0
      },
      "no_bulk_change" : {
         "fail" : 0,
         "pass" : 1,
         "undef" : 0
      },
      "no_duplicate" : {
         "fail" : 0,
         "pass" : 1,
         "undef" : 0
      },
      "no_long_message" : {
         "fail" : 0,
         "pass" : 1,
         "undef" : 0
      },
      "no_misspelling" : {
         "fail" : 0,
         "pass" : 1,
         "undef" : 0
      },
      "no_period_subject" : {
         "fail" : 0,
         "pass" : 1,
         "undef" : 0
      },
      "no_short_message" : {
         "fail" : 0,
         "pass" : 1,
         "undef" : 0
      },
      "no_vulgarity" : {
         "fail" : 0,
         "pass" : 1,
         "undef" : 0
      },
      "subject_limit" : {
         "fail" : 0,
         "pass" : 1,
         "undef" : 0
      }
   },
   "hartenfels@uni-koblenz.de" : {
      "body_limit" : {
         "fail" : 0,
         "pass" : 3,
         "undef" : 98
      },
      "body_used" : {
         "fail" : 98,
         "pass" : 3,
         "undef" : 0
      },
      "capitalize_subject" : {
         "fail" : 2,
         "pass" : 99,
         "undef" : 0
      },
      "empty_second_line" : {
         "fail" : 0,
         "pass" : 3,
         "undef" : 98
      },
      "imperative_subject" : {
         "fail" : 75,
         "pass" : 26,
         "undef" : 0
      },
      "no_bulk_change" : {
         "fail" : 6,
         "pass" : 95,
         "undef" : 0
      },
      "no_duplicate" : {
         "fail" : 2,
         "pass" : 99,
         "undef" : 0
      },
      "no_long_message" : {
         "fail" : 5,
         "pass" : 96,
         "undef" : 0
      },
      "no_misspelling" : {
         "fail" : 7,
         "pass" : 94,
         "undef" : 0
      },
      "no_period_subject" : {
         "fail" : 76,
         "pass" : 25,
         "undef" : 0
      },
      "no_short_message" : {
         "fail" : 15,
         "pass" : 86,
         "undef" : 0
      },
      "no_vulgarity" : {
         "fail" : 0,
         "pass" : 101,
         "undef" : 0
      },
      "subject_limit" : {
         "fail" : 11,
         "pass" : 90,
         "undef" : 0
      }
   },
   "kevin.k1252@gmail.com" : {
      "body_limit" : {
         "fail" : 1,
         "pass" : 2,
         "undef" : 147
      },
      "body_used" : {
         "fail" : 147,
         "pass" : 3,
         "undef" : 0
      },
      "capitalize_subject" : {
         "fail" : 120,
         "pass" : 30,
         "undef" : 0
      },
      "empty_second_line" : {
         "fail" : 0,
         "pass" : 3,
         "undef" : 147
      },
      "imperative_subject" : {
         "fail" : 117,
         "pass" : 33,
         "undef" : 0
      },
      "no_bulk_change" : {
         "fail" : 15,
         "pass" : 135,
         "undef" : 0
      },
      "no_duplicate" : {
         "fail" : 33,
         "pass" : 117,
         "undef" : 0
      },
      "no_long_message" : {
         "fail" : 2,
         "pass" : 148,
         "undef" : 0
      },
      "no_misspelling" : {
         "fail" : 7,
         "pass" : 143,
         "undef" : 0
      },
      "no_period_subject" : {
         "fail" : 0,
         "pass" : 150,
         "undef" : 0
      },
      "no_short_message" : {
         "fail" : 33,
         "pass" : 117,
         "undef" : 0
      },
      "no_vulgarity" : {
         "fail" : 0,
         "pass" : 150,
         "undef" : 0
      },
      "subject_limit" : {
         "fail" : 31,
         "pass" : 119,
         "undef" : 0
      }
   },
   "kevin@kevin-virtualbox.(none)" : {
      "body_limit" : {
         "fail" : 0,
         "pass" : 0,
         "undef" : 3
      },
      "body_used" : {
         "fail" : 3,
         "pass" : 0,
         "undef" : 0
      },
      "capitalize_subject" : {
         "fail" : 2,
         "pass" : 1,
         "undef" : 0
      },
      "empty_second_line" : {
         "fail" : 0,
         "pass" : 0,
         "undef" : 3
      },
      "imperative_subject" : {
         "fail" : 2,
         "pass" : 1,
         "undef" : 0
      },
      "no_bulk_change" : {
         "fail" : 0,
         "pass" : 3,
         "undef" : 0
      },
      "no_duplicate" : {
         "fail" : 1,
         "pass" : 2,
         "undef" : 0
      },
      "no_long_message" : {
         "fail" : 0,
         "pass" : 3,
         "undef" : 0
      },
      "no_misspelling" : {
         "fail" : 0,
         "pass" : 3,
         "undef" : 0
      },
      "no_period_subject" : {
         "fail" : 0,
         "pass" : 3,
         "undef" : 0
      },
      "no_short_message" : {
         "fail" : 1,
         "pass" : 2,
         "undef" : 0
      },
      "no_vulgarity" : {
         "fail" : 0,
         "pass" : 3,
         "undef" : 0
      },
      "subject_limit" : {
         "fail" : 1,
         "pass" : 2,
         "undef" : 0
      }
   },
   "kevin@tabolo.de" : {
      "body_limit" : {
         "fail" : 0,
         "pass" : 0,
         "undef" : 2
      },
      "body_used" : {
         "fail" : 2,
         "pass" : 0,
         "undef" : 0
      },
      "capitalize_subject" : {
         "fail" : 2,
         "pass" : 0,
         "undef" : 0
      },
      "empty_second_line" : {
         "fail" : 0,
         "pass" : 0,
         "undef" : 2
      },
      "imperative_subject" : {
         "fail" : 2,
         "pass" : 0,
         "undef" : 0
      },
      "no_bulk_change" : {
         "fail" : 0,
         "pass" : 2,
         "undef" : 0
      },
      "no_duplicate" : {
         "fail" : 0,
         "pass" : 2,
         "undef" : 0
      },
      "no_long_message" : {
         "fail" : 0,
         "pass" : 2,
         "undef" : 0
      },
      "no_misspelling" : {
         "fail" : 0,
         "pass" : 2,
         "undef" : 0
      },
      "no_period_subject" : {
         "fail" : 0,
         "pass" : 2,
         "undef" : 0
      },
      "no_short_message" : {
         "fail" : 0,
         "pass" : 2,
         "undef" : 0
      },
      "no_vulgarity" : {
         "fail" : 0,
         "pass" : 2,
         "undef" : 0
      },
      "subject_limit" : {
         "fail" : 0,
         "pass" : 2,
         "undef" : 0
      }
   },
   "l.schmelzeisen@gmx.de" : {
      "body_limit" : {
         "fail" : 1,
         "pass" : 0,
         "undef" : 3
      },
      "body_used" : {
         "fail" : 3,
         "pass" : 1,
         "undef" : 0
      },
      "capitalize_subject" : {
         "fail" : 0,
         "pass" : 4,
         "undef" : 0
      },
      "empty_second_line" : {
         "fail" : 0,
         "pass" : 1,
         "undef" : 3
      },
      "imperative_subject" : {
         "fail" : 0,
         "pass" : 4,
         "undef" : 0
      },
      "no_bulk_change" : {
         "fail" : 0,
         "pass" : 4,
         "undef" : 0
      },
      "no_duplicate" : {
         "fail" : 0,
         "pass" : 4,
         "undef" : 0
      },
      "no_long_message" : {
         "fail" : 1,
         "pass" : 3,
         "undef" : 0
      },
      "no_misspelling" : {
         "fail" : 1,
         "pass" : 3,
         "undef" : 0
      },
      "no_period_subject" : {
         "fail" : 3,
         "pass" : 1,
         "undef" : 0
      },
      "no_short_message" : {
         "fail" : 0,
         "pass" : 4,
         "undef" : 0
      },
      "no_vulgarity" : {
         "fail" : 0,
         "pass" : 4,
         "undef" : 0
      },
      "subject_limit" : {
         "fail" : 1,
         "pass" : 3,
         "undef" : 0
      }
   },
   "lukas@uni-koblenz.de" : {
      "body_limit" : {
         "fail" : 0,
         "pass" : 0,
         "undef" : 1
      },
      "body_used" : {
         "fail" : 1,
         "pass" : 0,
         "undef" : 0
      },
      "capitalize_subject" : {
         "fail" : 0,
         "pass" : 1,
         "undef" : 0
      },
      "empty_second_line" : {
         "fail" : 0,
         "pass" : 0,
         "undef" : 1
      },
      "imperative_subject" : {
         "fail" : 1,
         "pass" : 0,
         "undef" : 0
      },
      "no_bulk_change" : {
         "fail" : 0,
         "pass" : 1,
         "undef" : 0
      },
      "no_duplicate" : {
         "fail" : 0,
         "pass" : 1,
         "undef" : 0
      },
      "no_long_message" : {
         "fail" : 1,
         "pass" : 0,
         "undef" : 0
      },
      "no_misspelling" : {
         "fail" : 1,
         "pass" : 0,
         "undef" : 0
      },
      "no_period_subject" : {
         "fail" : 0,
         "pass" : 1,
         "undef" : 0
      },
      "no_short_message" : {
         "fail" : 0,
         "pass" : 1,
         "undef" : 0
      },
      "no_vulgarity" : {
         "fail" : 0,
         "pass" : 1,
         "undef" : 0
      },
      "subject_limit" : {
         "fail" : 1,
         "pass" : 0,
         "undef" : 0
      }
   },
   "martin.leinberger@googlemail.com" : {
      "body_limit" : {
         "fail" : 13,
         "pass" : 25,
         "undef" : 305
      },
      "body_used" : {
         "fail" : 305,
         "pass" : 38,
         "undef" : 0
      },
      "capitalize_subject" : {
         "fail" : 246,
         "pass" : 97,
         "undef" : 0
      },
      "empty_second_line" : {
         "fail" : 4,
         "pass" : 34,
         "undef" : 305
      },
      "imperative_subject" : {
         "fail" : 257,
         "pass" : 86,
         "undef" : 0
      },
      "no_bulk_change" : {
         "fail" : 29,
         "pass" : 314,
         "undef" : 0
      },
      "no_duplicate" : {
         "fail" : 31,
         "pass" : 312,
         "undef" : 0
      },
      "no_long_message" : {
         "fail" : 31,
         "pass" : 312,
         "undef" : 0
      },
      "no_misspelling" : {
         "fail" : 47,
         "pass" : 296,
         "undef" : 0
      },
      "no_period_subject" : {
         "fail" : 3,
         "pass" : 340,
         "undef" : 0
      },
      "no_short_message" : {
         "fail" : 45,
         "pass" : 298,
         "undef" : 0
      },
      "no_vulgarity" : {
         "fail" : 1,
         "pass" : 342,
         "undef" : 0
      },
      "subject_limit" : {
         "fail" : 82,
         "pass" : 261,
         "undef" : 0
      }
   },
   "martin@martin-desktop-ubuntu.(none)" : {
      "body_limit" : {
         "fail" : 0,
         "pass" : 0,
         "undef" : 1
      },
      "body_used" : {
         "fail" : 1,
         "pass" : 0,
         "undef" : 0
      },
      "capitalize_subject" : {
         "fail" : 1,
         "pass" : 0,
         "undef" : 0
      },
      "empty_second_line" : {
         "fail" : 0,
         "pass" : 0,
         "undef" : 1
      },
      "imperative_subject" : {
         "fail" : 1,
         "pass" : 0,
         "undef" : 0
      },
      "no_bulk_change" : {
         "fail" : 1,
         "pass" : 0,
         "undef" : 0
      },
      "no_duplicate" : {
         "fail" : 0,
         "pass" : 1,
         "undef" : 0
      },
      "no_long_message" : {
         "fail" : 0,
         "pass" : 1,
         "undef" : 0
      },
      "no_misspelling" : {
         "fail" : 0,
         "pass" : 1,
         "undef" : 0
      },
      "no_period_subject" : {
         "fail" : 0,
         "pass" : 1,
         "undef" : 0
      },
      "no_short_message" : {
         "fail" : 0,
         "pass" : 1,
         "undef" : 0
      },
      "no_vulgarity" : {
         "fail" : 0,
         "pass" : 1,
         "undef" : 0
      },
      "subject_limit" : {
         "fail" : 0,
         "pass" : 1,
         "undef" : 0
      }
   },
   "megaplanet.github@megaplanet.org" : {
      "body_limit" : {
         "fail" : 0,
         "pass" : 0,
         "undef" : 87
      },
      "body_used" : {
         "fail" : 87,
         "pass" : 0,
         "undef" : 0
      },
      "capitalize_subject" : {
         "fail" : 79,
         "pass" : 8,
         "undef" : 0
      },
      "empty_second_line" : {
         "fail" : 0,
         "pass" : 0,
         "undef" : 87
      },
      "imperative_subject" : {
         "fail" : 73,
         "pass" : 14,
         "undef" : 0
      },
      "no_bulk_change" : {
         "fail" : 8,
         "pass" : 79,
         "undef" : 0
      },
      "no_duplicate" : {
         "fail" : 31,
         "pass" : 56,
         "undef" : 0
      },
      "no_long_message" : {
         "fail" : 17,
         "pass" : 70,
         "undef" : 0
      },
      "no_misspelling" : {
         "fail" : 11,
         "pass" : 76,
         "undef" : 0
      },
      "no_period_subject" : {
         "fail" : 4,
         "pass" : 83,
         "undef" : 0
      },
      "no_short_message" : {
         "fail" : 33,
         "pass" : 54,
         "undef" : 0
      },
      "no_vulgarity" : {
         "fail" : 0,
         "pass" : 87,
         "undef" : 0
      },
      "subject_limit" : {
         "fail" : 28,
         "pass" : 59,
         "undef" : 0
      }
   },
   "mmonschau@users.noreply.github.com" : {
      "body_limit" : {
         "fail" : 0,
         "pass" : 1,
         "undef" : 10
      },
      "body_used" : {
         "fail" : 10,
         "pass" : 1,
         "undef" : 0
      },
      "capitalize_subject" : {
         "fail" : 0,
         "pass" : 11,
         "undef" : 0
      },
      "empty_second_line" : {
         "fail" : 0,
         "pass" : 1,
         "undef" : 10
      },
      "imperative_subject" : {
         "fail" : 10,
         "pass" : 1,
         "undef" : 0
      },
      "no_bulk_change" : {
         "fail" : 0,
         "pass" : 11,
         "undef" : 0
      },
      "no_duplicate" : {
         "fail" : 8,
         "pass" : 3,
         "undef" : 0
      },
      "no_long_message" : {
         "fail" : 0,
         "pass" : 11,
         "undef" : 0
      },
      "no_misspelling" : {
         "fail" : 0,
         "pass" : 11,
         "undef" : 0
      },
      "no_period_subject" : {
         "fail" : 0,
         "pass" : 11,
         "undef" : 0
      },
      "no_short_message" : {
         "fail" : 9,
         "pass" : 2,
         "undef" : 0
      },
      "no_vulgarity" : {
         "fail" : 0,
         "pass" : 11,
         "undef" : 0
      },
      "subject_limit" : {
         "fail" : 0,
         "pass" : 11,
         "undef" : 0
      }
   },
   "nicolas-beck@gmx.de" : {
      "body_limit" : {
         "fail" : 1,
         "pass" : 0,
         "undef" : 25
      },
      "body_used" : {
         "fail" : 25,
         "pass" : 1,
         "undef" : 0
      },
      "capitalize_subject" : {
         "fail" : 22,
         "pass" : 4,
         "undef" : 0
      },
      "empty_second_line" : {
         "fail" : 0,
         "pass" : 1,
         "undef" : 25
      },
      "imperative_subject" : {
         "fail" : 22,
         "pass" : 4,
         "undef" : 0
      },
      "no_bulk_change" : {
         "fail" : 0,
         "pass" : 26,
         "undef" : 0
      },
      "no_duplicate" : {
         "fail" : 14,
         "pass" : 12,
         "undef" : 0
      },
      "no_long_message" : {
         "fail" : 2,
         "pass" : 24,
         "undef" : 0
      },
      "no_misspelling" : {
         "fail" : 0,
         "pass" : 26,
         "undef" : 0
      },
      "no_period_subject" : {
         "fail" : 0,
         "pass" : 26,
         "undef" : 0
      },
      "no_short_message" : {
         "fail" : 6,
         "pass" : 20,
         "undef" : 0
      },
      "no_vulgarity" : {
         "fail" : 0,
         "pass" : 26,
         "undef" : 0
      },
      "subject_limit" : {
         "fail" : 5,
         "pass" : 21,
         "undef" : 0
      }
   },
   "rlaemmel@gmail.com" : {
      "body_limit" : {
         "fail" : 1,
         "pass" : 6,
         "undef" : 213
      },
      "body_used" : {
         "fail" : 213,
         "pass" : 7,
         "undef" : 0
      },
      "capitalize_subject" : {
         "fail" : 22,
         "pass" : 198,
         "undef" : 0
      },
      "empty_second_line" : {
         "fail" : 7,
         "pass" : 0,
         "undef" : 213
      },
      "imperative_subject" : {
         "fail" : 176,
         "pass" : 44,
         "undef" : 0
      },
      "no_bulk_change" : {
         "fail" : 29,
         "pass" : 191,
         "undef" : 0
      },
      "no_duplicate" : {
         "fail" : 78,
         "pass" : 142,
         "undef" : 0
      },
      "no_long_message" : {
         "fail" : 10,
         "pass" : 210,
         "undef" : 0
      },
      "no_misspelling" : {
         "fail" : 11,
         "pass" : 209,
         "undef" : 0
      },
      "no_period_subject" : {
         "fail" : 42,
         "pass" : 178,
         "undef" : 0
      },
      "no_short_message" : {
         "fail" : 104,
         "pass" : 116,
         "undef" : 0
      },
      "no_vulgarity" : {
         "fail" : 0,
         "pass" : 220,
         "undef" : 0
      },
      "subject_limit" : {
         "fail" : 29,
         "pass" : 191,
         "undef" : 0
      }
   },
   "ruether@uni-koblenz.de" : {
      "body_limit" : {
         "fail" : 0,
         "pass" : 0,
         "undef" : 5
      },
      "body_used" : {
         "fail" : 5,
         "pass" : 0,
         "undef" : 0
      },
      "capitalize_subject" : {
         "fail" : 2,
         "pass" : 3,
         "undef" : 0
      },
      "empty_second_line" : {
         "fail" : 0,
         "pass" : 0,
         "undef" : 5
      },
      "imperative_subject" : {
         "fail" : 3,
         "pass" : 2,
         "undef" : 0
      },
      "no_bulk_change" : {
         "fail" : 0,
         "pass" : 5,
         "undef" : 0
      },
      "no_duplicate" : {
         "fail" : 2,
         "pass" : 3,
         "undef" : 0
      },
      "no_long_message" : {
         "fail" : 0,
         "pass" : 5,
         "undef" : 0
      },
      "no_misspelling" : {
         "fail" : 0,
         "pass" : 5,
         "undef" : 0
      },
      "no_period_subject" : {
         "fail" : 0,
         "pass" : 5,
         "undef" : 0
      },
      "no_short_message" : {
         "fail" : 0,
         "pass" : 5,
         "undef" : 0
      },
      "no_vulgarity" : {
         "fail" : 0,
         "pass" : 5,
         "undef" : 0
      },
      "subject_limit" : {
         "fail" : 2,
         "pass" : 3,
         "undef" : 0
      }
   },
   "seiferphilipp@gmail.com" : {
      "body_limit" : {
         "fail" : 0,
         "pass" : 1,
         "undef" : 0
      },
      "body_used" : {
         "fail" : 0,
         "pass" : 1,
         "undef" : 0
      },
      "capitalize_subject" : {
         "fail" : 0,
         "pass" : 1,
         "undef" : 0
      },
      "empty_second_line" : {
         "fail" : 0,
         "pass" : 1,
         "undef" : 0
      },
      "imperative_subject" : {
         "fail" : 0,
         "pass" : 1,
         "undef" : 0
      },
      "no_bulk_change" : {
         "fail" : 0,
         "pass" : 1,
         "undef" : 0
      },
      "no_duplicate" : {
         "fail" : 0,
         "pass" : 1,
         "undef" : 0
      },
      "no_long_message" : {
         "fail" : 0,
         "pass" : 1,
         "undef" : 0
      },
      "no_misspelling" : {
         "fail" : 1,
         "pass" : 0,
         "undef" : 0
      },
      "no_period_subject" : {
         "fail" : 0,
         "pass" : 1,
         "undef" : 0
      },
      "no_short_message" : {
         "fail" : 0,
         "pass" : 1,
         "undef" : 0
      },
      "no_vulgarity" : {
         "fail" : 0,
         "pass" : 1,
         "undef" : 0
      },
      "subject_limit" : {
         "fail" : 0,
         "pass" : 1,
         "undef" : 0
      }
   },
   "t.moehlenhof@gmail.com" : {
      "body_limit" : {
         "fail" : 0,
         "pass" : 0,
         "undef" : 12
      },
      "body_used" : {
         "fail" : 12,
         "pass" : 0,
         "undef" : 0
      },
      "capitalize_subject" : {
         "fail" : 4,
         "pass" : 8,
         "undef" : 0
      },
      "empty_second_line" : {
         "fail" : 0,
         "pass" : 0,
         "undef" : 12
      },
      "imperative_subject" : {
         "fail" : 8,
         "pass" : 4,
         "undef" : 0
      },
      "no_bulk_change" : {
         "fail" : 0,
         "pass" : 12,
         "undef" : 0
      },
      "no_duplicate" : {
         "fail" : 2,
         "pass" : 10,
         "undef" : 0
      },
      "no_long_message" : {
         "fail" : 0,
         "pass" : 12,
         "undef" : 0
      },
      "no_misspelling" : {
         "fail" : 0,
         "pass" : 12,
         "undef" : 0
      },
      "no_period_subject" : {
         "fail" : 0,
         "pass" : 12,
         "undef" : 0
      },
      "no_short_message" : {
         "fail" : 7,
         "pass" : 5,
         "undef" : 0
      },
      "no_vulgarity" : {
         "fail" : 0,
         "pass" : 12,
         "undef" : 0
      },
      "subject_limit" : {
         "fail" : 0,
         "pass" : 12,
         "undef" : 0
      }
   },
   "tschmorleiz@googlemail.com" : {
      "body_limit" : {
         "fail" : 0,
         "pass" : 1,
         "undef" : 283
      },
      "body_used" : {
         "fail" : 283,
         "pass" : 1,
         "undef" : 0
      },
      "capitalize_subject" : {
         "fail" : 106,
         "pass" : 178,
         "undef" : 0
      },
      "empty_second_line" : {
         "fail" : 0,
         "pass" : 1,
         "undef" : 283
      },
      "imperative_subject" : {
         "fail" : 235,
         "pass" : 49,
         "undef" : 0
      },
      "no_bulk_change" : {
         "fail" : 4,
         "pass" : 280,
         "undef" : 0
      },
      "no_duplicate" : {
         "fail" : 178,
         "pass" : 106,
         "undef" : 0
      },
      "no_long_message" : {
         "fail" : 0,
         "pass" : 284,
         "undef" : 0
      },
      "no_misspelling" : {
         "fail" : 4,
         "pass" : 280,
         "undef" : 0
      },
      "no_period_subject" : {
         "fail" : 3,
         "pass" : 281,
         "undef" : 0
      },
      "no_short_message" : {
         "fail" : 111,
         "pass" : 173,
         "undef" : 0
      },
      "no_vulgarity" : {
         "fail" : 0,
         "pass" : 284,
         "undef" : 0
      },
      "subject_limit" : {
         "fail" : 32,
         "pass" : 252,
         "undef" : 0
      }
   },
   "worker@101companies.org" : {
      "body_limit" : {
         "fail" : 0,
         "pass" : 0,
         "undef" : 18
      },
      "body_used" : {
         "fail" : 18,
         "pass" : 0,
         "undef" : 0
      },
      "capitalize_subject" : {
         "fail" : 10,
         "pass" : 8,
         "undef" : 0
      },
      "empty_second_line" : {
         "fail" : 0,
         "pass" : 0,
         "undef" : 18
      },
      "imperative_subject" : {
         "fail" : 13,
         "pass" : 5,
         "undef" : 0
      },
      "no_bulk_change" : {
         "fail" : 0,
         "pass" : 18,
         "undef" : 0
      },
      "no_duplicate" : {
         "fail" : 2,
         "pass" : 16,
         "undef" : 0
      },
      "no_long_message" : {
         "fail" : 1,
         "pass" : 17,
         "undef" : 0
      },
      "no_misspelling" : {
         "fail" : 1,
         "pass" : 17,
         "undef" : 0
      },
      "no_period_subject" : {
         "fail" : 1,
         "pass" : 17,
         "undef" : 0
      },
      "no_short_message" : {
         "fail" : 6,
         "pass" : 12,
         "undef" : 0
      },
      "no_vulgarity" : {
         "fail" : 0,
         "pass" : 18,
         "undef" : 0
      },
      "subject_limit" : {
         "fail" : 3,
         "pass" : 15,
         "undef" : 0
      }
   },
   "worker@worker.uni-koblenz.de" : {
      "body_limit" : {
         "fail" : 0,
         "pass" : 1,
         "undef" : 2
      },
      "body_used" : {
         "fail" : 2,
         "pass" : 1,
         "undef" : 0
      },
      "capitalize_subject" : {
         "fail" : 1,
         "pass" : 2,
         "undef" : 0
      },
      "empty_second_line" : {
         "fail" : 0,
         "pass" : 1,
         "undef" : 2
      },
      "imperative_subject" : {
         "fail" : 2,
         "pass" : 1,
         "undef" : 0
      },
      "no_bulk_change" : {
         "fail" : 0,
         "pass" : 3,
         "undef" : 0
      },
      "no_duplicate" : {
         "fail" : 1,
         "pass" : 2,
         "undef" : 0
      },
      "no_long_message" : {
         "fail" : 0,
         "pass" : 3,
         "undef" : 0
      },
      "no_misspelling" : {
         "fail" : 1,
         "pass" : 2,
         "undef" : 0
      },
      "no_period_subject" : {
         "fail" : 0,
         "pass" : 3,
         "undef" : 0
      },
      "no_short_message" : {
         "fail" : 0,
         "pass" : 3,
         "undef" : 0
      },
      "no_vulgarity" : {
         "fail" : 0,
         "pass" : 3,
         "undef" : 0
      },
      "subject_limit" : {
         "fail" : 2,
         "pass" : 1,
         "undef" : 0
      }
   }
}
